CRUD/__init__.py
CRUD/asgi.py
CRUD/settings.py
CRUD/urls.py
CRUD/wsgi.py
CRUDXWORKERTEJAS1899-0.4.data/scripts/manage.py
boot_django/__init__.py
boot_django/boot_django.py
crudapp/__init__.py
crudapp/admin.py
crudapp/apps.py
crudapp/forms.py
crudapp/models.py
crudapp/tests.py
crudapp/views.py
crudapp/migrations/0001_initial.py
crudapp/migrations/__init__.py
CRUDXWORKERTEJAS1899-0.4.dist-info/LICENSE.txt
CRUDXWORKERTEJAS1899-0.4.dist-info/METADATA
CRUDXWORKERTEJAS1899-0.4.dist-info/WHEEL
CRUDXWORKERTEJAS1899-0.4.dist-info/top_level.txt
CRUDXWORKERTEJAS1899-0.4.dist-info/RECORD
